docsy/__init__.py
docsy/__main__.py
docsy/sample/README.md
docsy/sample/__config__.yml
docsy/sample/requirements.txt
docsy-0.11.3.dist-info/METADATA
docsy-0.11.3.dist-info/WHEEL
docsy-0.11.3.dist-info/entry_points.txt
docsy-0.11.3.dist-info/top_level.txt
docsy-0.11.3.dist-info/RECORD
